bitbucket_migration/__init__.py
bitbucket_migration/exceptions.py
bitbucket_migration/migrate_bitbucket_to_github.py
bitbucket_migration/audit/__init__.py
bitbucket_migration/audit/audit_orchestrator.py
bitbucket_migration/audit/audit_utils.py
bitbucket_migration/audit/auditor.py
bitbucket_migration/clients/__init__.py
bitbucket_migration/clients/bitbucket_client.py
bitbucket_migration/clients/github_client.py
bitbucket_migration/commands/audit_command.py
bitbucket_migration/commands/clean_command.py
bitbucket_migration/commands/cross_link_command.py
bitbucket_migration/commands/migration_command.py
bitbucket_migration/commands/test_auth_command.py
bitbucket_migration/config/__init__.py
bitbucket_migration/config/migration_config.py
bitbucket_migration/config/secure_config.py
bitbucket_migration/core/migration_context.py
bitbucket_migration/core/migration_orchestrator.py
bitbucket_migration/core/repo_migrator.py
bitbucket_migration/formatters/__init__.py
bitbucket_migration/formatters/content_formatter.py
bitbucket_migration/formatters/formatter_factory.py
bitbucket_migration/migration/cross_link_updater.py
bitbucket_migration/migration/issue_migrator.py
bitbucket_migration/migration/milestone_migrator.py
bitbucket_migration/migration/pr_migrator.py
bitbucket_migration/migration/report_generator.py
bitbucket_migration/services/__init__.py
bitbucket_migration/services/attachment_handler.py
bitbucket_migration/services/base_link_handler.py
bitbucket_migration/services/branch_link_handler.py
bitbucket_migration/services/commit_link_handler.py
bitbucket_migration/services/compare_link_handler.py
bitbucket_migration/services/cross_repo_link_handler.py
bitbucket_migration/services/cross_repo_mapping_store.py
bitbucket_migration/services/issue_link_handler.py
bitbucket_migration/services/link_detector.py
bitbucket_migration/services/link_rewriter.py
bitbucket_migration/services/pr_link_handler.py
bitbucket_migration/services/repo_home_link_handler.py
bitbucket_migration-1.0.0.dist-info/licenses/LICENSE.txt
bitbucket_migration-1.0.0.dist-info/METADATA
bitbucket_migration-1.0.0.dist-info/WHEEL
bitbucket_migration-1.0.0.dist-info/entry_points.txt
bitbucket_migration-1.0.0.dist-info/top_level.txt
bitbucket_migration-1.0.0.dist-info/RECORD
