Metadata-Version: 2.4
Name: bitbucket-migration
Version: 1.0.0
Summary: Scripts to assist with the migration of a Bitbucket git repository to GitHub.
Author-email: FKloosterman <devfakl@gmail.com>
Requires-Python: >=3.12
License-File: LICENSE.txt
Requires-Dist: requests>=2.32.5
Requires-Dist: python-dotenv>=1.0.0
Requires-Dist: cryptography>=43.0.0
Requires-Dist: dotenv>=0.9.9
Dynamic: license-file
